<?xml version="1.0" encoding="UTF-8"?>
<!-- Generated by Fujitsu Interstage XWand B0255 -->
<linkbase xmlns:table="http://xbrl.org/2014/table" xmlns:gen="http://xbrl.org/2008/generic" xmlns="http://www.xbrl.org/2003/linkbase" xmlns:xsi="http://www.w3.org/2001/XMLSchema-instance" xmlns:label="http://xbrl.org/2008/label" xmlns:xlink="http://www.w3.org/1999/xlink" xmlns:xbrli="http://www.xbrl.org/2003/instance">
  <roleRef roleURI="http://www.xbrl.org/2008/role/label" xlink:type="simple" xlink:href="http://www.xbrl.org/2008/generic-label.xsd#standard-label"/>
  <roleRef roleURI="http://www.xbrl.org/2008/role/link" xlink:type="simple" xlink:href="http://www.xbrl.org/2008/generic-link.xsd#standard-link-role"/>
  <roleRef roleURI="http://www.eurofiling.info/xbrl/role/rc-code" xlink:type="simple" xlink:href="http://www.eurofiling.info/eu/fr/xbrl/ext/model.xsd#rc-code"/>
  <arcroleRef arcroleURI="http://xbrl.org/arcrole/2008/element-label" xlink:type="simple" xlink:href="http://www.xbrl.org/2008/generic-label.xsd#element-label"/>
  <gen:link xlink:type="extended" xlink:role="http://www.xbrl.org/2008/role/link">
    <loc xlink:type="locator" xlink:href="sr_ReestrZastrahovanPoDogStrah-rend.xml#ruleNode_9" xlink:label="ruleNode_9" xlink:title="ruleNode_9"/>
    <label:label xlink:type="resource" xlink:label="label_2" xlink:role="http://www.eurofiling.info/xbrl/role/rc-code" xlink:title="label" xml:lang="ru" id="label_2">1</label:label>
    <gen:arc xlink:type="arc" xlink:arcrole="http://xbrl.org/arcrole/2008/element-label" xlink:from="ruleNode_9" xlink:to="label_2" xlink:title="ruleNode to label" priority="0" order="1.0"/>
    <loc xlink:type="locator" xlink:href="sr_ReestrZastrahovanPoDogStrah-rend.xml#ruleNode_13" xlink:label="ruleNode_42" xlink:title="ruleNode_42"/>
    <label:label xlink:type="resource" xlink:label="label_3" xlink:role="http://www.eurofiling.info/xbrl/role/rc-code" xlink:title="label" xml:lang="ru" id="label_3">2</label:label>
    <gen:arc xlink:type="arc" xlink:arcrole="http://xbrl.org/arcrole/2008/element-label" xlink:from="ruleNode_42" xlink:to="label_3" xlink:title="ruleNode to label" priority="0" order="1.0"/>
    <loc xlink:type="locator" xlink:href="sr_ReestrZastrahovanPoDogStrah-rend.xml#ruleNode_14" xlink:label="ruleNode_43" xlink:title="ruleNode_43"/>
    <label:label xlink:type="resource" xlink:label="label_4" xlink:role="http://www.eurofiling.info/xbrl/role/rc-code" xlink:title="label" xml:lang="ru" id="label_4">3</label:label>
    <gen:arc xlink:type="arc" xlink:arcrole="http://xbrl.org/arcrole/2008/element-label" xlink:from="ruleNode_43" xlink:to="label_4" xlink:title="ruleNode to label" priority="0" order="1.0"/>
    <loc xlink:type="locator" xlink:href="sr_ReestrZastrahovanPoDogStrah-rend.xml#ruleNode" xlink:label="ruleNode" xlink:title="ruleNode"/>
    <label:label xlink:type="resource" xlink:label="label_5" xlink:role="http://www.eurofiling.info/xbrl/role/rc-code" xlink:title="label" xml:lang="ru" id="label_5">4</label:label>
    <gen:arc xlink:type="arc" xlink:arcrole="http://xbrl.org/arcrole/2008/element-label" xlink:from="ruleNode" xlink:to="label_5" xlink:title="ruleNode to label" priority="0" order="1.0"/>
    <loc xlink:type="locator" xlink:href="sr_ReestrZastrahovanPoDogStrah-rend.xml#ruleNode_11" xlink:label="ruleNode_11" xlink:title="ruleNode_11"/>
    <label:label xlink:type="resource" xlink:label="label_6" xlink:role="http://www.eurofiling.info/xbrl/role/rc-code" xlink:title="label" xml:lang="ru" id="label_6">5</label:label>
    <gen:arc xlink:type="arc" xlink:arcrole="http://xbrl.org/arcrole/2008/element-label" xlink:from="ruleNode_11" xlink:to="label_6" xlink:title="ruleNode to label" priority="0" order="1.0"/>
    <loc xlink:type="locator" xlink:href="sr_ReestrZastrahovanPoDogStrah-rend.xml#ruleNode_2" xlink:label="ruleNode_2" xlink:title="ruleNode_2"/>
    <label:label xlink:type="resource" xlink:label="label_7" xlink:role="http://www.eurofiling.info/xbrl/role/rc-code" xlink:title="label" xml:lang="ru" id="label_7">6</label:label>
    <gen:arc xlink:type="arc" xlink:arcrole="http://xbrl.org/arcrole/2008/element-label" xlink:from="ruleNode_2" xlink:to="label_7" xlink:title="ruleNode to label" priority="0" order="1.0"/>
    <loc xlink:type="locator" xlink:href="sr_ReestrZastrahovanPoDogStrah-rend.xml#ruleNode_3" xlink:label="ruleNode_3" xlink:title="ruleNode_3"/>
    <label:label xlink:type="resource" xlink:label="label_8" xlink:role="http://www.eurofiling.info/xbrl/role/rc-code" xlink:title="label" xml:lang="ru" id="label_8">7</label:label>
    <gen:arc xlink:type="arc" xlink:arcrole="http://xbrl.org/arcrole/2008/element-label" xlink:from="ruleNode_3" xlink:to="label_8" xlink:title="ruleNode to label" priority="0" order="1.0"/>
    <loc xlink:type="locator" xlink:href="sr_ReestrZastrahovanPoDogStrah-rend.xml#ruleNode_5" xlink:label="ruleNode_5" xlink:title="ruleNode_5"/>
    <label:label xlink:type="resource" xlink:label="label_10" xlink:role="http://www.eurofiling.info/xbrl/role/rc-code" xlink:title="label" xml:lang="ru" id="label_10">8</label:label>
    <gen:arc xlink:type="arc" xlink:arcrole="http://xbrl.org/arcrole/2008/element-label" xlink:from="ruleNode_5" xlink:to="label_10" xlink:title="ruleNode to label" priority="0" order="1.0"/>
    <loc xlink:type="locator" xlink:href="sr_ReestrZastrahovanPoDogStrah-rend.xml#ruleNode_6" xlink:label="ruleNode_6" xlink:title="ruleNode_6"/>
    <label:label xlink:type="resource" xlink:label="label_11" xlink:role="http://www.eurofiling.info/xbrl/role/rc-code" xlink:title="label" xml:lang="ru" id="label_11">9</label:label>
    <gen:arc xlink:type="arc" xlink:arcrole="http://xbrl.org/arcrole/2008/element-label" xlink:from="ruleNode_6" xlink:to="label_11" xlink:title="ruleNode to label" priority="0" order="1.0"/>
    <loc xlink:type="locator" xlink:href="sr_ReestrZastrahovanPoDogStrah-rend.xml#ruleNode_7" xlink:label="ruleNode_7" xlink:title="ruleNode_7"/>
    <label:label xlink:type="resource" xlink:label="label_12" xlink:role="http://www.eurofiling.info/xbrl/role/rc-code" xlink:title="label" xml:lang="ru" id="label_12">10</label:label>
    <gen:arc xlink:type="arc" xlink:arcrole="http://xbrl.org/arcrole/2008/element-label" xlink:from="ruleNode_7" xlink:to="label_12" xlink:title="ruleNode to label" priority="0" order="1.0"/>
    <loc xlink:type="locator" xlink:href="sr_ReestrZastrahovanPoDogStrah-rend.xml#ruleNode_8" xlink:label="ruleNode_8" xlink:title="ruleNode_8"/>
    <label:label xlink:type="resource" xlink:label="label_13" xlink:role="http://www.eurofiling.info/xbrl/role/rc-code" xlink:title="label" xml:lang="ru" id="label_13">11</label:label>
    <gen:arc xlink:type="arc" xlink:arcrole="http://xbrl.org/arcrole/2008/element-label" xlink:from="ruleNode_8" xlink:to="label_13" xlink:title="ruleNode to label" priority="0" order="1.0"/>
    <loc xlink:type="locator" xlink:href="sr_ReestrZastrahovanPoDogStrah-rend.xml#ruleNode_10" xlink:label="ruleNode_10" xlink:title="ruleNode_10"/>
    <label:label xlink:type="resource" xlink:label="label_14" xlink:role="http://www.eurofiling.info/xbrl/role/rc-code" xlink:title="label" xml:lang="ru" id="label_14">12</label:label>
    <gen:arc xlink:type="arc" xlink:arcrole="http://xbrl.org/arcrole/2008/element-label" xlink:from="ruleNode_10" xlink:to="label_14" xlink:title="ruleNode to label" priority="0" order="1.0"/>
    <loc xlink:type="locator" xlink:href="sr_ReestrZastrahovanPoDogStrah-rend.xml#ruleNode_12" xlink:label="ruleNode_12" xlink:title="ruleNode_12"/>
    <label:label xlink:type="resource" xlink:label="label_15" xlink:role="http://www.eurofiling.info/xbrl/role/rc-code" xlink:title="label" xml:lang="ru" id="label_15">13</label:label>
    <gen:arc xlink:type="arc" xlink:arcrole="http://xbrl.org/arcrole/2008/element-label" xlink:from="ruleNode_12" xlink:to="label_15" xlink:title="ruleNode to label" priority="0" order="1.0"/>
    <loc xlink:type="locator" xlink:href="sr_ReestrZastrahovanPoDogStrah-rend.xml#ruleNode_15" xlink:label="ruleNode_15" xlink:title="ruleNode_15"/>
    <label:label xlink:type="resource" xlink:label="label_18" xlink:role="http://www.eurofiling.info/xbrl/role/rc-code" xlink:title="label" xml:lang="ru" id="label_18">14</label:label>
    <gen:arc xlink:type="arc" xlink:arcrole="http://xbrl.org/arcrole/2008/element-label" xlink:from="ruleNode_15" xlink:to="label_18" xlink:title="ruleNode to label" priority="0" order="1.0"/>
    <loc xlink:type="locator" xlink:href="sr_ReestrZastrahovanPoDogStrah-rend.xml#ruleNode_16" xlink:label="ruleNode_16" xlink:title="ruleNode_16"/>
    <label:label xlink:type="resource" xlink:label="label_19" xlink:role="http://www.eurofiling.info/xbrl/role/rc-code" xlink:title="label" xml:lang="ru" id="label_19">15</label:label>
    <gen:arc xlink:type="arc" xlink:arcrole="http://xbrl.org/arcrole/2008/element-label" xlink:from="ruleNode_16" xlink:to="label_19" xlink:title="ruleNode to label" priority="0" order="1.0"/>
    <loc xlink:type="locator" xlink:href="sr_ReestrZastrahovanPoDogStrah-rend.xml#ruleNode_17" xlink:label="ruleNode_17" xlink:title="ruleNode_17"/>
    <label:label xlink:type="resource" xlink:label="label_20" xlink:role="http://www.eurofiling.info/xbrl/role/rc-code" xlink:title="label" xml:lang="ru" id="label_20">16</label:label>
    <gen:arc xlink:type="arc" xlink:arcrole="http://xbrl.org/arcrole/2008/element-label" xlink:from="ruleNode_17" xlink:to="label_20" xlink:title="ruleNode to label" priority="0" order="1.0"/>
    <loc xlink:type="locator" xlink:href="sr_ReestrZastrahovanPoDogStrah-rend.xml#ruleNode_18" xlink:label="ruleNode_18" xlink:title="ruleNode_18"/>
    <label:label xlink:type="resource" xlink:label="label_21" xlink:role="http://www.eurofiling.info/xbrl/role/rc-code" xlink:title="label" xml:lang="ru" id="label_21">17</label:label>
    <gen:arc xlink:type="arc" xlink:arcrole="http://xbrl.org/arcrole/2008/element-label" xlink:from="ruleNode_18" xlink:to="label_21" xlink:title="ruleNode to label" priority="0" order="1.0"/>
    <loc xlink:type="locator" xlink:href="sr_ReestrZastrahovanPoDogStrah-rend.xml#ruleNode_19" xlink:label="ruleNode_19" xlink:title="ruleNode_19"/>
    <label:label xlink:type="resource" xlink:label="label_22" xlink:role="http://www.eurofiling.info/xbrl/role/rc-code" xlink:title="label" xml:lang="ru" id="label_22">18</label:label>
    <gen:arc xlink:type="arc" xlink:arcrole="http://xbrl.org/arcrole/2008/element-label" xlink:from="ruleNode_19" xlink:to="label_22" xlink:title="ruleNode to label" priority="0" order="1.0"/>
    <loc xlink:type="locator" xlink:href="sr_ReestrZastrahovanPoDogStrah-rend.xml#ruleNode_20" xlink:label="ruleNode_20" xlink:title="ruleNode_20"/>
    <label:label xlink:type="resource" xlink:label="label_23" xlink:role="http://www.eurofiling.info/xbrl/role/rc-code" xlink:title="label" xml:lang="ru" id="label_23">19</label:label>
    <gen:arc xlink:type="arc" xlink:arcrole="http://xbrl.org/arcrole/2008/element-label" xlink:from="ruleNode_20" xlink:to="label_23" xlink:title="ruleNode to label" priority="0" order="1.0"/>
    <loc xlink:type="locator" xlink:href="sr_ReestrZastrahovanPoDogStrah-rend.xml#ruleNode_21" xlink:label="ruleNode_21" xlink:title="ruleNode_21"/>
    <label:label xlink:type="resource" xlink:label="label_24" xlink:role="http://www.eurofiling.info/xbrl/role/rc-code" xlink:title="label" xml:lang="ru" id="label_24">20</label:label>
    <gen:arc xlink:type="arc" xlink:arcrole="http://xbrl.org/arcrole/2008/element-label" xlink:from="ruleNode_21" xlink:to="label_24" xlink:title="ruleNode to label" priority="0" order="1.0"/>
    <loc xlink:type="locator" xlink:href="sr_ReestrZastrahovanPoDogStrah-rend.xml#ruleNode_22" xlink:label="ruleNode_22" xlink:title="ruleNode_22"/>
    <label:label xlink:type="resource" xlink:label="label_25" xlink:role="http://www.eurofiling.info/xbrl/role/rc-code" xlink:title="label" xml:lang="ru" id="label_25">21</label:label>
    <gen:arc xlink:type="arc" xlink:arcrole="http://xbrl.org/arcrole/2008/element-label" xlink:from="ruleNode_22" xlink:to="label_25" xlink:title="ruleNode to label" priority="0" order="1.0"/>
    <loc xlink:type="locator" xlink:href="sr_ReestrZastrahovanPoDogStrah-rend.xml#ruleNode_23" xlink:label="ruleNode_23" xlink:title="ruleNode_23"/>
    <label:label xlink:type="resource" xlink:label="label_26" xlink:role="http://www.eurofiling.info/xbrl/role/rc-code" xlink:title="label" xml:lang="ru" id="label_26">22</label:label>
    <gen:arc xlink:type="arc" xlink:arcrole="http://xbrl.org/arcrole/2008/element-label" xlink:from="ruleNode_23" xlink:to="label_26" xlink:title="ruleNode to label" priority="0" order="1.0"/>
    <loc xlink:type="locator" xlink:href="sr_ReestrZastrahovanPoDogStrah-rend.xml#ruleNode_24" xlink:label="ruleNode_24" xlink:title="ruleNode_24"/>
    <label:label xlink:type="resource" xlink:label="label_27" xlink:role="http://www.eurofiling.info/xbrl/role/rc-code" xlink:title="label" xml:lang="ru" id="label_27">23</label:label>
    <gen:arc xlink:type="arc" xlink:arcrole="http://xbrl.org/arcrole/2008/element-label" xlink:from="ruleNode_24" xlink:to="label_27" xlink:title="ruleNode to label" priority="0" order="1.0"/>
    <loc xlink:type="locator" xlink:href="sr_ReestrZastrahovanPoDogStrah-rend.xml#ruleNode_25" xlink:label="ruleNode_25" xlink:title="ruleNode_25"/>
    <label:label xlink:type="resource" xlink:label="label_28" xlink:role="http://www.eurofiling.info/xbrl/role/rc-code" xlink:title="label" xml:lang="ru" id="label_28">24</label:label>
    <gen:arc xlink:type="arc" xlink:arcrole="http://xbrl.org/arcrole/2008/element-label" xlink:from="ruleNode_25" xlink:to="label_28" xlink:title="ruleNode to label" priority="0" order="1.0"/>
    <loc xlink:type="locator" xlink:href="sr_ReestrZastrahovanPoDogStrah-rend.xml#ruleNode_26" xlink:label="ruleNode_26" xlink:title="ruleNode_26"/>
    <label:label xlink:type="resource" xlink:label="label_29" xlink:role="http://www.eurofiling.info/xbrl/role/rc-code" xlink:title="label" xml:lang="ru" id="label_29">25</label:label>
    <gen:arc xlink:type="arc" xlink:arcrole="http://xbrl.org/arcrole/2008/element-label" xlink:from="ruleNode_26" xlink:to="label_29" xlink:title="ruleNode to label" priority="0" order="1.0"/>
    <loc xlink:type="locator" xlink:href="sr_ReestrZastrahovanPoDogStrah-rend.xml#ruleNode_27" xlink:label="ruleNode_27" xlink:title="ruleNode_27"/>
    <label:label xlink:type="resource" xlink:label="label_30" xlink:role="http://www.eurofiling.info/xbrl/role/rc-code" xlink:title="label" xml:lang="ru" id="label_30">26</label:label>
    <gen:arc xlink:type="arc" xlink:arcrole="http://xbrl.org/arcrole/2008/element-label" xlink:from="ruleNode_27" xlink:to="label_30" xlink:title="ruleNode to label" priority="0" order="1.0"/>
    <loc xlink:type="locator" xlink:href="sr_ReestrZastrahovanPoDogStrah-rend.xml#ruleNode_28" xlink:label="ruleNode_28" xlink:title="ruleNode_28"/>
    <label:label xlink:type="resource" xlink:label="label_31" xlink:role="http://www.eurofiling.info/xbrl/role/rc-code" xlink:title="label" xml:lang="ru" id="label_31">27</label:label>
    <gen:arc xlink:type="arc" xlink:arcrole="http://xbrl.org/arcrole/2008/element-label" xlink:from="ruleNode_28" xlink:to="label_31" xlink:title="ruleNode to label" priority="0" order="1.0"/>
    <loc xlink:type="locator" xlink:href="sr_ReestrZastrahovanPoDogStrah-rend.xml#ruleNode_29" xlink:label="ruleNode_29" xlink:title="ruleNode_29"/>
    <label:label xlink:type="resource" xlink:label="label_32" xlink:role="http://www.eurofiling.info/xbrl/role/rc-code" xlink:title="label" xml:lang="ru" id="label_32">28</label:label>
    <gen:arc xlink:type="arc" xlink:arcrole="http://xbrl.org/arcrole/2008/element-label" xlink:from="ruleNode_29" xlink:to="label_32" xlink:title="ruleNode to label" priority="0" order="1.0"/>
    <loc xlink:type="locator" xlink:href="sr_ReestrZastrahovanPoDogStrah-rend.xml#ruleNode_30" xlink:label="ruleNode_30" xlink:title="ruleNode_30"/>
    <label:label xlink:type="resource" xlink:label="label_33" xlink:role="http://www.eurofiling.info/xbrl/role/rc-code" xlink:title="label" xml:lang="ru" id="label_33">29</label:label>
    <gen:arc xlink:type="arc" xlink:arcrole="http://xbrl.org/arcrole/2008/element-label" xlink:from="ruleNode_30" xlink:to="label_33" xlink:title="ruleNode to label" priority="0" order="1.0"/>
    <loc xlink:type="locator" xlink:href="sr_ReestrZastrahovanPoDogStrah-rend.xml#ruleNode_31" xlink:label="ruleNode_31" xlink:title="ruleNode_31"/>
    <label:label xlink:type="resource" xlink:label="label_34" xlink:role="http://www.eurofiling.info/xbrl/role/rc-code" xlink:title="label" xml:lang="ru" id="label_34">30</label:label>
    <gen:arc xlink:type="arc" xlink:arcrole="http://xbrl.org/arcrole/2008/element-label" xlink:from="ruleNode_31" xlink:to="label_34" xlink:title="ruleNode to label" priority="0" order="1.0"/>
    <loc xlink:type="locator" xlink:href="sr_ReestrZastrahovanPoDogStrah-rend.xml#ruleNode_32" xlink:label="ruleNode_32" xlink:title="ruleNode_32"/>
    <label:label xlink:type="resource" xlink:label="label_35" xlink:role="http://www.eurofiling.info/xbrl/role/rc-code" xlink:title="label" xml:lang="ru" id="label_35">31</label:label>
    <gen:arc xlink:type="arc" xlink:arcrole="http://xbrl.org/arcrole/2008/element-label" xlink:from="ruleNode_32" xlink:to="label_35" xlink:title="ruleNode to label" priority="0" order="1.0"/>
    <loc xlink:type="locator" xlink:href="sr_ReestrZastrahovanPoDogStrah-rend.xml#ruleNode_33" xlink:label="ruleNode_33" xlink:title="ruleNode_33"/>
    <label:label xlink:type="resource" xlink:label="label_36" xlink:role="http://www.eurofiling.info/xbrl/role/rc-code" xlink:title="label" xml:lang="ru" id="label_36">32</label:label>
    <gen:arc xlink:type="arc" xlink:arcrole="http://xbrl.org/arcrole/2008/element-label" xlink:from="ruleNode_33" xlink:to="label_36" xlink:title="ruleNode to label" priority="0" order="1.0"/>
    <loc xlink:type="locator" xlink:href="sr_ReestrZastrahovanPoDogStrah-rend.xml#ruleNode_34" xlink:label="ruleNode_34" xlink:title="ruleNode_34"/>
    <label:label xlink:type="resource" xlink:label="label_37" xlink:role="http://www.eurofiling.info/xbrl/role/rc-code" xlink:title="label" xml:lang="ru" id="label_37">33</label:label>
    <gen:arc xlink:type="arc" xlink:arcrole="http://xbrl.org/arcrole/2008/element-label" xlink:from="ruleNode_34" xlink:to="label_37" xlink:title="ruleNode to label" priority="0" order="1.0"/>
    <loc xlink:type="locator" xlink:href="sr_ReestrZastrahovanPoDogStrah-rend.xml#ruleNode_35" xlink:label="ruleNode_35" xlink:title="ruleNode_35"/>
    <label:label xlink:type="resource" xlink:label="label_38" xlink:role="http://www.eurofiling.info/xbrl/role/rc-code" xlink:title="label" xml:lang="ru" id="label_38">34</label:label>
    <gen:arc xlink:type="arc" xlink:arcrole="http://xbrl.org/arcrole/2008/element-label" xlink:from="ruleNode_35" xlink:to="label_38" xlink:title="ruleNode to label" priority="0" order="1.0"/>
    <loc xlink:type="locator" xlink:href="sr_ReestrZastrahovanPoDogStrah-rend.xml#ruleNode_36" xlink:label="ruleNode_36" xlink:title="ruleNode_36"/>
    <label:label xlink:type="resource" xlink:label="label_39" xlink:role="http://www.eurofiling.info/xbrl/role/rc-code" xlink:title="label" xml:lang="ru" id="label_39">35</label:label>
    <gen:arc xlink:type="arc" xlink:arcrole="http://xbrl.org/arcrole/2008/element-label" xlink:from="ruleNode_36" xlink:to="label_39" xlink:title="ruleNode to label" priority="0" order="1.0"/>
    <loc xlink:type="locator" xlink:href="sr_ReestrZastrahovanPoDogStrah-rend.xml#ruleNode_37" xlink:label="ruleNode_37" xlink:title="ruleNode_37"/>
    <label:label xlink:type="resource" xlink:label="label_40" xlink:role="http://www.eurofiling.info/xbrl/role/rc-code" xlink:title="label" xml:lang="ru" id="label_40">36</label:label>
    <gen:arc xlink:type="arc" xlink:arcrole="http://xbrl.org/arcrole/2008/element-label" xlink:from="ruleNode_37" xlink:to="label_40" xlink:title="ruleNode to label" priority="0" order="1.0"/>
    <loc xlink:type="locator" xlink:href="sr_ReestrZastrahovanPoDogStrah-rend.xml#ruleNode_38" xlink:label="ruleNode_38" xlink:title="ruleNode_38"/>
    <label:label xlink:type="resource" xlink:label="label_41" xlink:role="http://www.eurofiling.info/xbrl/role/rc-code" xlink:title="label" xml:lang="ru" id="label_41">37</label:label>
    <gen:arc xlink:type="arc" xlink:arcrole="http://xbrl.org/arcrole/2008/element-label" xlink:from="ruleNode_38" xlink:to="label_41" xlink:title="ruleNode to label" priority="0" order="1.0"/>
    <loc xlink:type="locator" xlink:href="sr_ReestrZastrahovanPoDogStrah-rend.xml#sr_ReestrZastrahovanPoDogStrah" xlink:label="table" xlink:title="table"/>
    <label:label xlink:type="resource" xlink:label="label" xlink:role="http://www.xbrl.org/2008/role/label" xlink:title="label" xml:lang="ru" id="label">Форма 3. Реестр полисов (застрахованных) по договорам страхования жизни</label:label>
    <gen:arc xlink:type="arc" xlink:arcrole="http://xbrl.org/arcrole/2008/element-label" xlink:from="table" xlink:to="label" xlink:title="table to label" priority="0" order="1.0"/>
  </gen:link>
</linkbase>
